inside_out_proxy/__init__.py
inside_out_proxy/axlog.py
inside_out_proxy/inside_out_proxy
inside_out_proxy/inside_out_proxy_test_jobserver
inside_out_proxy/proxy.py
inside_out_proxy/version.py
inside_out_proxy/assets/__init__.py
inside_out_proxy/assets/testserver_playbooks/__init__.py
inside_out_proxy/assets/testserver_playbooks/bin1.py
inside_out_proxy/assets/testserver_playbooks/prod.py
inside_out_proxy/assets/testserver_playbooks/testserver.py
inside_out_proxy-190126.data/scripts/inside_out_proxy
inside_out_proxy-190126.data/scripts/inside_out_proxy_test_jobserver
inside_out_proxy-190126.dist-info/LICENSE.txt
inside_out_proxy-190126.dist-info/METADATA
inside_out_proxy-190126.dist-info/RECORD
inside_out_proxy-190126.dist-info/WHEEL
inside_out_proxy-190126.dist-info/top_level.txt
